MANIFEST.in
README.md
setup.py
fardel/__init__.py
fardel/app.py
fardel/config.py
fardel/ext.py
fardel/manager.py
fardel.egg-info/PKG-INFO
fardel.egg-info/SOURCES.txt
fardel.egg-info/dependency_links.txt
fardel.egg-info/requires.txt
fardel.egg-info/top_level.txt
fardel/core/__init__.py
fardel/core/base.py
fardel/core/email.py
fardel/core/rest.py
fardel/core/seo.py
fardel/core/utils.py
fardel/core/auth/__init__.py
fardel/core/auth/models.py
fardel/core/auth/views.py
fardel/core/auth/templates/confirm_email.html
fardel/core/auth/templates/confirm_email.txt
fardel/core/media/__init__.py
fardel/core/media/models.py
fardel/core/media/views.py
fardel/core/panel/__init__.py
fardel/core/panel/decorator.py
fardel/core/panel/sidebar.py
fardel/core/panel/template_tags.py
fardel/core/panel/static/tinymce.min.js
fardel/core/panel/static/css/bootstrap.min.css
fardel/core/panel/static/css/bootstrap.min.css.map
fardel/core/panel/static/css/custom.css
fardel/core/panel/static/css/custom.ltr.css
fardel/core/panel/static/css/dropzone.min.css
fardel/core/panel/static/css/font-awesome.min.css
fardel/core/panel/static/css/ionicons.min.css
fardel/core/panel/static/css/login.css
fardel/core/panel/static/css/nprogress.css
fardel/core/panel/static/css/select2.min.css
fardel/core/panel/static/fonts/BYekan.ttf
fardel/core/panel/static/fonts/glyphicons-halflings-regular.woff2
fardel/core/panel/static/js/bootstrap.min.js
fardel/core/panel/static/js/bootstrap.min.js.map
fardel/core/panel/static/js/custom.js
fardel/core/panel/static/js/dropzone.min.js
fardel/core/panel/static/js/fastclick.js
fardel/core/panel/static/js/jquery.min.js
fardel/core/panel/static/js/moment.min.js
fardel/core/panel/static/js/nprogress.js
fardel/core/panel/static/js/popper.min.js
fardel/core/panel/static/js/select2.min.js
fardel/core/panel/static/js/tooltip.min.js
fardel/core/panel/static/plugins/advlist/plugin.min.js
fardel/core/panel/static/plugins/anchor/plugin.min.js
fardel/core/panel/static/plugins/autolink/plugin.min.js
fardel/core/panel/static/plugins/autoresize/plugin.min.js
fardel/core/panel/static/plugins/autosave/plugin.min.js
